Workbook

Sheet Checklist
A1: Fase | B1: Descrição | C1: Fazer | D1: Feito
A2: 00 - Alinhamento e problema | B2: Definir a decisão de negócio em uma frase (ex.: aprovar ou negar crédito com score de inadimplência) | C2: Sim | D2: Não
A3: 00 - Alinhamento e problema | B3: Identificar patrocinador, usuários e quem audita o modelo | C3: Sim | D3: Não
A4: 00 - Alinhamento e problema | B4: Definir escopo: o que está dentro e fora do projeto | C4: Sim | D4: Não
A5: 00 - Alinhamento e problema | B5: Definir tipo de problema de ML (ex.: classificação binária com classe rara ~6,7%) | C5: Sim | D5: Não
A6: 00 - Alinhamento e problema | B6: Definir variável alvo e janela de observação (ex.: SeriousDlqin2yrs, atraso 90+ em 2 anos) | C6: Sim | D6: Não
A7: 00 - Alinhamento e problema | B7: Definir critérios de sucesso técnicos (AUC, KS, calibração) e de negócio (inadimplência, aprovação, R$) | C7: Sim | D7: Não
A8: 00 - Alinhamento e problema | B8: Levantar premissas financeiras (custo de aprovar mau pagador, margem de bom pagador) e registrar em arquivo único | C8: Sim | D8: Não
A9: 00 - Alinhamento e problema | B9: Levantar restrições: regulação, LGPD, prazo, plataforma, orçamento | C9: Sim | D9: Não
A10: 00 - Alinhamento e problema | B10: Inventariar fontes de dados (treino, scoring, dicionário) e defasagem do rótulo | C10: Sim | D10: Não
A11: 00 - Alinhamento e problema | B11: Registrar riscos conhecidos (viés, vazamento de dados, drift, rótulo atrasado) | C11: Sim | D11: Não
A12: 00 - Alinhamento e problema | B12: Listar questões em aberto para validar com o patrocinador | C12: Sim | D12: Não
... A165: 18 - Divulgação e encerramento | B165: Revisão final: limpar .temp e .temp_del, conferir .gitignore e arquivar o projeto | C165: Sim | D165: Não

Sheet Resumo
A1: Progresso por fase
A2: Calculado por fórmulas a partir da aba Checklist (colunas Fazer e Feito). Itens marcados N/A em Fazer saem do cálculo.
A4: Fase | B4: Itens | C4: A fazer | D4: Feitos | E4: % concluído
A5: 00 - Alinhamento e problema | B5: =COUNTIF(Checklist!$A$2:$A$165,A5) -> 13 | C5: =COUNTIFS(Checklist!$A$2:$A$165,A5,Checklist!$C$2:$C$165,"Sim") -> 13 | D5: =COUNTIFS(Checklist!$A$2:$A$165,A5,Checklist!$C$2:$C$165,"Sim",Checklist!$D$2:$D$165,"Sim") -> 0 | E5: =IF(C5=0,0,D5/C5) -> 0
A6: 01 - Hipóteses e perguntas | B6: =COUNTIF(Checklist!$A$2:$A$165,A6) -> 8 | C6: =COUNTIFS(Checklist!$A$2:$A$165,A6,Checklist!$C$2:$C$165,"Sim") -> 8 | D6: =COUNTIFS(Checklist!$A$2:$A$165,A6,Checklist!$C$2:$C$165,"Sim",Checklist!$D$2:$D$165,"Sim") -> 0 | E6: =IF(C6=0,0,D6/C6) -> 0
A7: 02 - Planejamento técnico e arquitetura | B7: =COUNTIF(Checklist!$A$2:$A$165,A7) -> 9 | C7: =COUNTIFS(Checklist!$A$2:$A$165,A7,Checklist!$C$2:$C$165,"Sim") -> 9 | D7: =COUNTIFS(Checklist!$A$2:$A$165,A7,Checklist!$C$2:$C$165,"Sim",Checklist!$D$2:$D$165,"Sim") -> 0 | E7: =IF(C7=0,0,D7/C7) -> 0
A8: 03 - Repositório e ferramentas | B8: =COUNTIF(Checklist!$A$2:$A$165,A8) -> 12 | C8: =COUNTIFS(Checklist!$A$2:$A$165,A8,Checklist!$C$2:$C$165,"Sim") -> 12 | D8: =COUNTIFS(Checklist!$A$2:$A$165,A8,Checklist!$C$2:$C$165,"Sim",Checklist!$D$2:$D$165,"Sim") -> 0 | E8: =IF(C8=0,0,D8/C8) -> 0
A9: 04 - Infraestrutura por ambiente | B9: =COUNTIF(Checklist!$A$2:$A$165,A9) -> 7 | C9: =COUNTIFS(Checklist!$A$2:$A$165,A9,Checklist!$C$2:$C$165,"Sim") -> 7 | D9: =COUNTIFS(Checklist!$A$2:$A$165,A9,Checklist!$C$2:$C$165,"Sim",Checklist!$D$2:$D$165,"Sim") -> 0 | E9: =IF(C9=0,0,D9/C9) -> 0
A10: 05 - Ingestão Bronze | B10: =COUNTIF(Checklist!$A$2:$A$165,A10) -> 6 | C10: =COUNTIFS(Checklist!$A$2:$A$165,A10,Checklist!$C$2:$C$165,"Sim") -> 6 | D10: =COUNTIFS(Checklist!$A$2:$A$165,A10,Checklist!$C$2:$C$165,"Sim",Checklist!$D$2:$D$165,"Sim") -> 0 | E10: =IF(C10=0,0,D10/C10) -> 0
A11: 06 - Silver | B11: =COUNTIF(Checklist!$A$2:$A$165,A11) -> 6 | C11: =COUNTIFS(Checklist!$A$2:$A$165,A11,Checklist!$C$2:$C$165,"Sim") -> 6 | D11: =COUNTIFS(Checklist!$A$2:$A$165,A11,Checklist!$C$2:$C$165,"Sim",Checklist!$D$2:$D$165,"Sim") -> 0 | E11: =IF(C11=0,0,D11/C11) -> 0
A12: 07 - Gold e dicionário de dados | B12: =COUNTIF(Checklist!$A$2:$A$165,A12) -> 8 | C12: =COUNTIFS(Checklist!$A$2:$A$165,A12,Checklist!$C$2:$C$165,"Sim") -> 8 | D12: =COUNTIFS(Checklist!$A$2:$A$165,A12,Checklist!$C$2:$C$165,"Sim",Checklist!$D$2:$D$165,"Sim") -> 0 | E12: =IF(C12=0,0,D12/C12) -> 0
A13: 08 - EDA e qualidade de dados | B13: =COUNTIF(Checklist!$A$2:$A$165,A13) -> 7 | C13: =COUNTIFS(Checklist!$A$2:$A$165,A13,Checklist!$C$2:$C$165,"Sim") -> 7 | D13: =COUNTIFS(Checklist!$A$2:$A$165,A13,Checklist!$C$2:$C$165,"Sim",Checklist!$D$2:$D$165,"Sim") -> 0 | E13: =IF(C13=0,0,D13/C13) -> 0
A14: 09 - Validação das hipóteses (DEV) | B14: =COUNTIF(Checklist!$A$2:$A$165,A14) -> 6 | C14: =COUNTIFS(Checklist!$A$2:$A$165,A14,Checklist!$C$2:$C$165,"Sim") -> 6 | D14: =COUNTIFS(Checklist!$A$2:$A$165,A14,Checklist!$C$2:$C$165,"Sim",Checklist!$D$2:$D$165,"Sim") -> 0 | E14: =IF(C14=0,0,D14/C14) -> 0
A15: 10 - Modelagem e treino | B15: =COUNTIF(Checklist!$A$2:$A$165,A15) -> 11 | C15: =COUNTIFS(Checklist!$A$2:$A$165,A15,Checklist!$C$2:$C$165,"Sim") -> 11 | D15: =COUNTIFS(Checklist!$A$2:$A$165,A15,Checklist!$C$2:$C$165,"Sim",Checklist!$D$2:$D$165,"Sim") -> 0 | E15: =IF(C15=0,0,D15/C15) -> 0
A16: 11 - Viés, calibração, threshold e ROI | B16: =COUNTIF(Checklist!$A$2:$A$165,A16) -> 10 | C16: =COUNTIFS(Checklist!$A$2:$A$165,A16,Checklist!$C$2:$C$165,"Sim") -> 10 | D16: =COUNTIFS(Checklist!$A$2:$A$165,A16,Checklist!$C$2:$C$165,"Sim",Checklist!$D$2:$D$165,"Sim") -> 0 | E16: =IF(C16=0,0,D16/C16) -> 0
... A23: 18 - Divulgação e encerramento | B23: =COUNTIF(Checklist!$A$2:$A$165,A23) -> 6 | C23: =COUNTIFS(Checklist!$A$2:$A$165,A23,Checklist!$C$2:$C$165,"Sim") -> 6 | D23: =COUNTIFS(Checklist!$A$2:$A$165,A23,Checklist!$C$2:$C$165,"Sim",Checklist!$D$2:$D$165,"Sim") -> 0 | E23: =IF(C23=0,0,D23/C23) -> 0
A24: TOTAL | B24: =SUM(B5:B23) -> 164 | C24: =SUM(C5:C23) -> 164 | D24: =SUM(D5:D23) -> 0 | E24: =IF(C24=0,0,D24/C24) -> 0

Sheet Como usar
A1: Como usar este checklist
A2: Base: projeto risco_credito_databricks (pipeline de score de crédito no Databricks, DEV → HML → PRD).
A4: Colunas da aba Checklist
A5: Fase: etapa do projeto, na ordem em que deve ser executada (00 a 18).
A6: Descrição: atividade a executar. Os nomes de arquivos e valores entre parênteses são exemplos do projeto de referência; adapte ao novo projeto.
A7: Fazer: Sim = atividade se aplica (padrão); N/A = não se aplica ao projeto (a linha fica cinza e sai do cálculo).
A8: Feito: altere de Não para Sim ao concluir (a linha fica riscada e a célula verde).
A10: Células que você edita: somente as colunas Fazer e Feito (listas suspensas). A aba Resumo é calculada sozinha.
A11: Dica: use o filtro da coluna Fase para trabalhar uma fase por vez; para projetos rápidos (POC), marque N/A nas fases de CI/CD, PRD e divulgação.
